barcode_label_printer/__init__.py
barcode_label_printer-0.1.0.dist-info/licenses/LICENSE
barcode_label_printer-0.1.0.dist-info/METADATA
barcode_label_printer-0.1.0.dist-info/WHEEL
barcode_label_printer-0.1.0.dist-info/top_level.txt
barcode_label_printer-0.1.0.dist-info/RECORD
