Metadata-Version: 2.4
Name: barcode-label-printer
Version: 0.1.0
Summary: A Python package for generating barcode labels and printing to various printers including Niimbot
Author-email: David Kang <david2004kang@gmail.com>
License: MIT
Project-URL: Homepage, https://github.com/david2004kang/barcode-label-printer
Project-URL: Documentation, https://github.com/david2004kang/barcode-label-printer#readme
Project-URL: Repository, https://github.com/david2004kang/barcode-label-printer
Project-URL: Issues, https://github.com/david2004kang/barcode-label-printer/issues
Keywords: barcode,label,printer,niimbot,svg,printing
Classifier: Development Status :: 3 - Alpha
Classifier: Intended Audience :: Developers
Classifier: License :: OSI Approved :: MIT License
Classifier: Programming Language :: Python :: 3
Classifier: Programming Language :: Python :: 3.8
Classifier: Programming Language :: Python :: 3.9
Classifier: Programming Language :: Python :: 3.10
Classifier: Programming Language :: Python :: 3.11
Classifier: Topic :: Printing
Classifier: Topic :: Software Development :: Libraries :: Python Modules
Requires-Python: >=3.8
License-File: LICENSE
Requires-Dist: python-barcode>=0.15.0
Requires-Dist: svgwrite>=1.4.0
Requires-Dist: reportlab>=3.6.0
Requires-Dist: PyPDF2>=3.0.0
Requires-Dist: pyserial>=3.5
Requires-Dist: pillow>=10.0.0
Provides-Extra: windows
Requires-Dist: pywin32>=306; extra == "windows"
Requires-Dist: cairosvg>=2.7.0; extra == "windows"
Provides-Extra: bluetooth
Requires-Dist: pybluez>=0.23; extra == "bluetooth"
Dynamic: license-file
